<annotation>
	<folder>image</folder>
	<filename>835.jpg</filename>
	<path>/home/shouryadey/Downloads/image/835.jpg</path>
	<source>
		<database>Unknown</database>
	</source>
	<size>
		<width>318</width>
		<height>159</height>
		<depth>3</depth>
	</size>
	<segmented>0</segmented>
	<object>
		<name>Gun</name>
		<pose>Unspecified</pose>
		<truncated>0</truncated>
		<difficult>0</difficult>
		<bndbox>
			<xmin>96</xmin>
			<ymin>38</ymin>
			<xmax>222</xmax>
			<ymax>78</ymax>
		</bndbox>
	</object>
</annotation>
